{
  "project_info": {
    "project_number": "224583824998",
    "firebase_url": "https://push-32f05.firebaseio.com",
    "project_id": "push-32f05",
    "storage_bucket": "push-32f05.appspot.com"
  },
  "client": [
    {
      "client_info": {
        "mobilesdk_app_id": "1:224583824998:android:764d2cb7da3280eb",
        "android_client_info": {
          "package_name": "io.ionic.starter"
        }
      },
      "oauth_client": [
        {
          "client_id": "224583824998-31h2chijgjtle2nbvc11lca9c1c29v62.apps.googleusercontent.com",
          "client_type": 3
        }
      ],
      "api_key": [
        {
          "current_key": "AIzaSyAmlGykOb-n3HdLRG7Mu5Kd0DZFduOmZdM"
        }
      ],
      "services": {
        "analytics_service": {
          "status": 1
        },
        "appinvite_service": {
          "status": 1,
          "other_platform_oauth_client": []
        },
        "ads_service": { 
          "status": 2
        }
      }
    }
  ],
  "configuration_version": "1"
}